[
  {
    "id": "6366b30c9b421bae55d18f3c",
    "name": "Champions League 2023-24",
    "description": "",
    "mode": 1,
    "participants": [
      {
        "id": "63627c815db2569f1b044daf",
        "name": "Inter Milan"
      },
      {
        "id": "63627c815db2569f1b044db0",
        "name": "Atlético Madrid"
      },
      {
        "id": "63627c815db2569f1b044db1",
        "name": "PSV Eindhoven"
      },
      {
        "id": "63627c815db2569f1b044db2",
        "name": "Borussia Dortmund"
      },
      {
        "id": "63627c815db2569f1b044db3",
        "name": "Paris Saint-Germain"
      },
      {
        "id": "63627c815db2569f1b044db4",
        "name": "Real Sociedad"
      },
      {
        "id": "63627c815db2569f1b044db5",
        "name": "Napoli"
      },
      {
        "id": "63627c815db2569f1b044db6",
        "name": "Barcelona"
      },
      {
        "id": "63627c815db2569f1b044db7",
        "name": "Porto"
      },
      {
        "id": "63627c815db2569f1b044db8",
        "name": "Arsenal"
      },
      {
        "id": "63627c815db2569f1b044db9",
        "name": "Lazio"
      },
      {
        "id": "63627c815db2569f1b044dba",
        "name": "Bayern Munich"
      },
      {
        "id": "63627c815db2569f1b044dbb",
        "name": "RB Leipzig"
      },
      {
        "id": "63627c815db2569f1b044dbc",
        "name": "Real Madrid"
      },
      {
        "id": "63627c815db2569f1b044dbd",
        "name": "Copenhagen"
      },
      {
        "id": "63627c815db2569f1b044dbe",
        "name": "Manchester City"
      }
    ],
    "rounds": [
      {
        "id": "674347eeacd28462e462fcbb",
        "index": 0,
        "format": 2,
        "matches": [
          {
            "p1": "63627c815db2569f1b044daf",
            "p2": "63627c815db2569f1b044db0",
            "format": 2,
            "games": [
              {
                "p1": 1,
                "p2": 0
              },
              {
                "p1": 1,
                "p2": 2,
                "tiebreaker": {
                  "p1": 2,
                  "p2": 3
                }
              }
            ],
            "won": "63627c815db2569f1b044db0",
            "lost": "63627c815db2569f1b044daf",
            "diff": 0
          },
          {
            "p1": "63627c815db2569f1b044db1",
            "p2": "63627c815db2569f1b044db2",
            "format": 2,
            "games": [
              {
                "p1": 1,
                "p2": 1
              },
              {
                "p1": 0,
                "p2": 2
              }
            ],
            "won": "63627c815db2569f1b044db2",
            "lost": "63627c815db2569f1b044db1",
            "diff": 0
          },
          {
            "p1": "63627c815db2569f1b044db3",
            "p2": "63627c815db2569f1b044db4",
            "format": 2,
            "games": [
              {
                "p1": 2,
                "p2": 0
              },
              {
                "p1": 2,
                "p2": 1
              }
            ],
            "won": "63627c815db2569f1b044db3",
            "lost": "63627c815db2569f1b044db4",
            "diff": 0
          },
          {
            "p1": "63627c815db2569f1b044db5",
            "p2": "63627c815db2569f1b044db6",
            "format": 2,
            "games": [
              {
                "p1": 1,
                "p2": 1
              },
              {
                "p1": 1,
                "p2": 3
              }
            ],
            "won": "63627c815db2569f1b044db6",
            "lost": "63627c815db2569f1b044db5",
            "diff": 0
          },
          {
            "p1": "63627c815db2569f1b044db7",
            "p2": "63627c815db2569f1b044db8",
            "format": 2,
            "games": [
              {
                "p1": 1,
                "p2": 0
              },
              {
                "p1": 0,
                "p2": 1,
                "tiebreaker": {
                  "p1": 2,
                  "p2": 4
                }
              }
            ],
            "won": "63627c815db2569f1b044db8",
            "lost": "63627c815db2569f1b044db7",
            "diff": 0
          },
          {
            "p1": "63627c815db2569f1b044db9",
            "p2": "63627c815db2569f1b044dba",
            "format": 2,
            "games": [
              {
                "p1": 1,
                "p2": 0
              },
              {
                "p1": 0,
                "p2": 3
              }
            ],
            "won": "63627c815db2569f1b044dba",
            "lost": "63627c815db2569f1b044db9",
            "diff": 0
          },
          {
            "p1": "63627c815db2569f1b044dbb",
            "p2": "63627c815db2569f1b044dbc",
            "format": 2,
            "games": [
              {
                "p1": 0,
                "p2": 1
              },
              {
                "p1": 1,
                "p2": 1
              }
            ],
            "won": "63627c815db2569f1b044dbc",
            "lost": "63627c815db2569f1b044dbb",
            "diff": 0
          },
          {
            "p1": "63627c815db2569f1b044dbd",
            "p2": "63627c815db2569f1b044dbe",
            "format": 2,
            "games": [
              {
                "p1": 1,
                "p2": 3
              },
              {
                "p1": 1,
                "p2": 3
              }
            ],
            "won": "63627c815db2569f1b044dbe",
            "lost": "63627c815db2569f1b044dbd",
            "diff": 0
          }
        ]
      },
      {
        "id": "674347eeacd28462e462fcbb",
        "index": 1,
        "format": 2,
        "matches": [
          {
            "p1": "63627c815db2569f1b044db0",
            "p2": "63627c815db2569f1b044db2",
            "format": 2,
            "games": [
              {
                "p1": 2,
                "p2": 1
              },
              {
                "p1": 2,
                "p2": 4
              }
            ],
            "won": "63627c815db2569f1b044db2",
            "lost": "63627c815db2569f1b044db0",
            "diff": 0
          },
          {
            "p1": "63627c815db2569f1b044db3",
            "p2": "63627c815db2569f1b044db6",
            "format": 2,
            "games": [
              {
                "p1": 2,
                "p2": 3
              },
              {
                "p1": 4,
                "p2": 1
              }
            ],
            "won": "63627c815db2569f1b044db3",
            "lost": "63627c815db2569f1b044db6",
            "diff": 0
          },
          {
            "p1": "63627c815db2569f1b044db8",
            "p2": "63627c815db2569f1b044dba",
            "format": 2,
            "games": [
              {
                "p1": 2,
                "p2": 2
              },
              {
                "p1": 0,
                "p2": 1
              }
            ],
            "won": "63627c815db2569f1b044dba",
            "lost": "63627c815db2569f1b044db8",
            "diff": 0
          },
          {
            "p1": "63627c815db2569f1b044dbc",
            "p2": "63627c815db2569f1b044dbe",
            "format": 2,
            "games": [
              {
                "p1": 3,
                "p2": 3
              },
              {
                "p1": 1,
                "p2": 1,
                "tiebreaker": {
                  "p1": 4,
                  "p2": 3
                }
              }
            ],
            "won": "63627c815db2569f1b044dbc",
            "lost": "63627c815db2569f1b044dbe",
            "diff": 0
          }
        ]
      },
      {
        "id": "674348aaaae3924a135552e2",
        "index": 2,
        "format": 2,
        "matches": [
          {
            "p1": "63627c815db2569f1b044db2",
            "p2": "63627c815db2569f1b044db3",
            "format": 2,
            "games": [
              {
                "p1": 1,
                "p2": 0
              },
              {
                "p1": 1,
                "p2": 0
              }
            ],
            "won": "63627c815db2569f1b044db2",
            "lost": "63627c815db2569f1b044db3",
            "diff": 0
          },
          {
            "p1": "63627c815db2569f1b044dba",
            "p2": "63627c815db2569f1b044dbc",
            "format": 2,
            "games": [
              {
                "p1": 2,
                "p2": 2
              },
              {
                "p1": 1,
                "p2": 2
              }
            ],
            "won": "63627c815db2569f1b044dbc",
            "lost": "63627c815db2569f1b044dba",
            "diff": 0
          }
        ]
      },
      {
        "id": "674348b01d61b2a2788d469a",
        "index": 3,
        "format": 1,
        "matches": [
          {
            "p1": "63627c815db2569f1b044db2",
            "p2": "63627c815db2569f1b044dbc",
            "format": 1,
            "games": [
              {
                "p1": 0,
                "p2": 2
              }
            ],
            "won": "63627c815db2569f1b044dbc",
            "lost": "63627c815db2569f1b044db2",
            "diff": 0
          }
        ]
      }
    ],
    "owner": "674117eee1d0fe2f52522080",
    "startedAt": "2023-09-21T00:00:00Z",
    "createdAt": 1667678539544,
    "createdBy": "674117eee1d0fe2f52522080",
    "completed": false,
    "deleted": false
  },
  {
    "id": "6366b30c9b421bae55d18f3d",
    "name": "PGL Major Copenhagen 2024",
    "description": "",
    "mode": 2,
    "participants": [
      {
        "id": "674124cc6e153ca1279dd0a5",
        "name": "FaZe Clan"
      },
      {
        "id": "674125068ab9aa45cfdd66ef",
        "name": "Team Spirit"
      },
      {
        "id": "6741250d916c7b74ed88e586",
        "name": "Team Vitality"
      },
      {
        "id": "6741251424962cdac652760a",
        "name": "Mouz"
      },
      {
        "id": "674125190253e44912294526",
        "name": "Complexity"
      },
      {
        "id": "67412529b148bf739d49828b",
        "name": "Virtus Pro"
      },
      {
        "id": "6741252f4aeabdb5905c3d0c",
        "name": "Natus Vincere"
      },
      {
        "id": "674125330a62bc77412439f9",
        "name": "G2 Esports"
      },
      {
        "id": "67412536aedffe2820ae3b0c",
        "name": "Heroic"
      },
      {
        "id": "67412539482b464c0f32299b",
        "name": "Cloud9"
      },
      {
        "id": "6741253c73252ce545e3c049",
        "name": "Eternal Fire"
      },
      {
        "id": "6741254025b609484e4a4820",
        "name": "ECSTATIC"
      },
      {
        "id": "67412543c987a8093fa50f3b",
        "name": "paiN Gaming"
      },
      {
        "id": "674125460fa99bd8bd6fc760",
        "name": "Imperial Esports"
      },
      {
        "id": "6741254df43c72a94f5cdd69",
        "name": "The MongolZ"
      },
      {
        "id": "674125498b0989883796ed77",
        "name": "FURIA"
      }
    ],
    "rounds": [
      {
        "id": "67435ac84605c274d73d16a2",
        "index": 0,
        "format": 1,
        "matches": [
          {
            "p1": "6741251424962cdac652760a",
            "p2": "6741254025b609484e4a4820",
            "format": 1,
            "games": [
              {
                "p1": 13,
                "p2": 11
              }
            ],
            "won": "6741251424962cdac652760a",
            "lost": "6741254025b609484e4a4820",
            "diff": 2
          },
          {
            "p1": "6741252f4aeabdb5905c3d0c",
            "p2": "6741254df43c72a94f5cdd69",
            "format": 1,
            "games": [
              {
                "p1": 13,
                "p2": 10
              }
            ],
            "won": "6741252f4aeabdb5905c3d0c",
            "lost": "6741254df43c72a94f5cdd69",
            "diff": 3
          },
          {
            "p1": "6741250d916c7b74ed88e586",
            "p2": "6741253c73252ce545e3c049",
            "format": 1,
            "games": [
              {
                "p1": 10,
                "p2": 13
              }
            ],
            "won": "6741253c73252ce545e3c049",
            "lost": "6741250d916c7b74ed88e586",
            "diff": 3
          },
          {
            "p1": "67412529b148bf739d49828b",
            "p2": "674125460fa99bd8bd6fc760",
            "format": 1,
            "games": [
              {
                "p1": 6,
                "p2": 13
              }
            ],
            "won": "674125460fa99bd8bd6fc760",
            "lost": "67412529b148bf739d49828b",
            "diff": 7
          },
          {
            "p1": "674124cc6e153ca1279dd0a5",
            "p2": "67412536aedffe2820ae3b0c",
            "format": 1,
            "games": [
              {
                "p1": 10,
                "p2": 13
              }
            ],
            "won": "67412536aedffe2820ae3b0c",
            "lost": "674124cc6e153ca1279dd0a5",
            "diff": 3
          },
          {
            "p1": "674125190253e44912294526",
            "p2": "67412543c987a8093fa50f3b",
            "format": 1,
            "games": [
              {
                "p1": 13,
                "p2": 9
              }
            ],
            "won": "674125190253e44912294526",
            "lost": "67412543c987a8093fa50f3b",
            "diff": 4
          },
          {
            "p1": "674125068ab9aa45cfdd66ef",
            "p2": "67412539482b464c0f32299b",
            "format": 1,
            "games": [
              {
                "p1": 13,
                "p2": 7
              }
            ],
            "won": "674125068ab9aa45cfdd66ef",
            "lost": "67412539482b464c0f32299b",
            "diff": 6
          },
          {
            "p1": "674125330a62bc77412439f9",
            "p2": "674125498b0989883796ed77",
            "format": 1,
            "games": [
              {
                "p1": 13,
                "p2": 3
              }
            ],
            "won": "674125330a62bc77412439f9",
            "lost": "674125498b0989883796ed77",
            "diff": 10
          }
        ]
      },
      {
        "id": "67435acdf28217f05cc0af4f",
        "index": 1,
        "format": 1,
        "matches": [
          {
            "p1": "6741251424962cdac652760a",
            "p2": "6741253c73252ce545e3c049",
            "format": 1,
            "games": [
              {
                "p1": 13,
                "p2": 11
              }
            ],
            "won": "6741251424962cdac652760a",
            "lost": "6741253c73252ce545e3c049",
            "diff": 2
          },
          {
            "p1": "674125190253e44912294526",
            "p2": "67412536aedffe2820ae3b0c",
            "format": 1,
            "games": [
              {
                "p1": 19,
                "p2": 17
              }
            ],
            "won": "674125190253e44912294526",
            "lost": "67412536aedffe2820ae3b0c",
            "diff": 2
          },
          {
            "p1": "6741252f4aeabdb5905c3d0c",
            "p2": "674125330a62bc77412439f9",
            "format": 1,
            "games": [
              {
                "p1": 13,
                "p2": 11
              }
            ],
            "won": "6741252f4aeabdb5905c3d0c",
            "lost": "674125330a62bc77412439f9",
            "diff": 2
          },
          {
            "p1": "674125068ab9aa45cfdd66ef",
            "p2": "674125460fa99bd8bd6fc760",
            "format": 1,
            "games": [
              {
                "p1": 13,
                "p2": 2
              }
            ],
            "won": "674125068ab9aa45cfdd66ef",
            "lost": "674125460fa99bd8bd6fc760",
            "diff": 11
          },
          {
            "p1": "6741250d916c7b74ed88e586",
            "p2": "6741254df43c72a94f5cdd69",
            "format": 1,
            "games": [
              {
                "p1": 13,
                "p2": 9
              }
            ],
            "won": "6741250d916c7b74ed88e586",
            "lost": "6741254df43c72a94f5cdd69",
            "diff": 4
          },
          {
            "p1": "67412529b148bf739d49828b",
            "p2": "67412543c987a8093fa50f3b",
            "format": 1,
            "games": [
              {
                "p1": 13,
                "p2": 9
              }
            ],
            "won": "67412529b148bf739d49828b",
            "lost": "67412543c987a8093fa50f3b",
            "diff": 4
          },
          {
            "p1": "67412539482b464c0f32299b",
            "p2": "6741254025b609484e4a4820",
            "format": 1,
            "games": [
              {
                "p1": 13,
                "p2": 3
              }
            ],
            "won": "67412539482b464c0f32299b",
            "lost": "6741254025b609484e4a4820",
            "diff": 10
          },
          {
            "p1": "674124cc6e153ca1279dd0a5",
            "p2": "674125498b0989883796ed77",
            "format": 1,
            "games": [
              {
                "p1": 13,
                "p2": 7
              }
            ],
            "won": "674124cc6e153ca1279dd0a5",
            "lost": "674125498b0989883796ed77",
            "diff": 6
          }
        ]
      },
      {
        "id": "67435ad15295275419f68a2e",
        "index": 2,
        "format": 1,
        "matches": [
          {
            "p1": "6741251424962cdac652760a",
            "p2": "674125190253e44912294526",
            "format": 1,
            "games": [
              {
                "p1": 13,
                "p2": 1
              },
              {
                "p1": 13,
                "p2": 2
              }
            ],
            "won": "6741251424962cdac652760a",
            "lost": "674125190253e44912294526",
            "diff": 23
          },
          {
            "p1": "674125068ab9aa45cfdd66ef",
            "p2": "6741252f4aeabdb5905c3d0c",
            "format": 1,
            "games": [
              {
                "p1": 13,
                "p2": 16
              },
              {
                "p1": 13,
                "p2": 9
              },
              {
                "p1": 13,
                "p2": 7
              }
            ],
            "won": "674125068ab9aa45cfdd66ef",
            "lost": "6741252f4aeabdb5905c3d0c",
            "diff": 7
          },
          {
            "p1": "67412536aedffe2820ae3b0c",
            "p2": "67412529b148bf739d49828b",
            "format": 1,
            "games": [
              {
                "p1": 13,
                "p2": 6
              }
            ],
            "won": "67412529b148bf739d49828b",
            "lost": "67412536aedffe2820ae3b0c",
            "diff": 7
          },
          {
            "p1": "674125330a62bc77412439f9",
            "p2": "67412539482b464c0f32299b",
            "format": 1,
            "games": [
              {
                "p1": 9,
                "p2": 13
              }
            ],
            "won": "67412539482b464c0f32299b",
            "lost": "674125330a62bc77412439f9",
            "diff": 4
          },
          {
            "p1": "6741253c73252ce545e3c049",
            "p2": "674124cc6e153ca1279dd0a5",
            "format": 1,
            "games": [
              {
                "p1": 13,
                "p2": 1
              }
            ],
            "won": "6741253c73252ce545e3c049",
            "lost": "674124cc6e153ca1279dd0a5",
            "diff": 12
          },
          {
            "p1": "674125460fa99bd8bd6fc760",
            "p2": "6741250d916c7b74ed88e586",
            "format": 1,
            "games": [
              {
                "p1": 9,
                "p2": 13
              }
            ],
            "won": "6741250d916c7b74ed88e586",
            "lost": "674125460fa99bd8bd6fc760",
            "diff": 4
          },
          {
            "p1": "67412543c987a8093fa50f3b",
            "p2": "6741254df43c72a94f5cdd69",
            "format": 1,
            "games": [
              {
                "p1": 9,
                "p2": 13
              },
              {
                "p1": 13,
                "p2": 10
              },
              {
                "p1": 22,
                "p2": 19
              }
            ],
            "won": "67412543c987a8093fa50f3b",
            "lost": "6741254df43c72a94f5cdd69",
            "diff": 2
          },
          {
            "p1": "6741254025b609484e4a4820",
            "p2": "674125498b0989883796ed77",
            "format": 1,
            "games": [
              {
                "p1": 13,
                "p2": 7
              },
              {
                "p1": 14,
                "p2": 16
              },
              {
                "p1": 13,
                "p2": 7
              }
            ],
            "won": "6741254025b609484e4a4820",
            "lost": "674125498b0989883796ed77",
            "diff": 10
          }
        ]
      },
      {
        "id": "67435ad5b8e45ed8daba771f",
        "index": 3,
        "format": 1,
        "matches": [
          {
            "p1": "6741253c73252ce545e3c049",
            "p2": "67412529b148bf739d49828b",
            "format": 1,
            "games": [
              {
                "p1": 6,
                "p2": 13
              },
              {
                "p1": 13,
                "p2": 6
              },
              {
                "p1": 13,
                "p2": 7
              }
            ],
            "won": "6741253c73252ce545e3c049",
            "lost": "67412529b148bf739d49828b",
            "diff": 6
          },
          {
            "p1": "674125190253e44912294526",
            "p2": "6741250d916c7b74ed88e586",
            "format": 1,
            "games": [
              {
                "p1": 16,
                "p2": 19
              },
              {
                "p1": 13,
                "p2": 7
              },
              {
                "p1": 10,
                "p2": 13
              }
            ],
            "won": "6741250d916c7b74ed88e586",
            "lost": "674125190253e44912294526",
            "diff": 0
          },
          {
            "p1": "67412539482b464c0f32299b",
            "p2": "6741252f4aeabdb5905c3d0c",
            "format": 1,
            "games": [
              {
                "p1": 14,
                "p2": 16
              },
              {
                "p1": 13,
                "p2": 6
              },
              {
                "p1": 13,
                "p2": 2
              }
            ],
            "won": "67412539482b464c0f32299b",
            "lost": "6741252f4aeabdb5905c3d0c",
            "diff": 16
          },
          {
            "p1": "674125460fa99bd8bd6fc760",
            "p2": "674124cc6e153ca1279dd0a5",
            "format": 1,
            "games": [
              {
                "p1": 8,
                "p2": 13
              },
              {
                "p1": 13,
                "p2": 8
              },
              {
                "p1": 8,
                "p2": 13
              }
            ],
            "won": "674124cc6e153ca1279dd0a5",
            "lost": "674125460fa99bd8bd6fc760",
            "diff": 5
          },
          {
            "p1": "6741254025b609484e4a4820",
            "p2": "674125330a62bc77412439f9",
            "format": 1,
            "games": [
              {
                "p1": 7,
                "p2": 13
              },
              {
                "p1": 13,
                "p2": 11
              },
              {
                "p1": 8,
                "p2": 13
              }
            ],
            "won": "674125330a62bc77412439f9",
            "lost": "6741254025b609484e4a4820",
            "diff": 9
          },
          {
            "p1": "67412536aedffe2820ae3b0c",
            "p2": "67412543c987a8093fa50f3b",
            "format": 1,
            "games": [
              {
                "p1": 6,
                "p2": 13
              },
              {
                "p1": 9,
                "p2": 13
              }
            ],
            "won": "67412543c987a8093fa50f3b",
            "lost": "67412536aedffe2820ae3b0c",
            "diff": 11
          }
        ]
      },
      {
        "id": "67435ad96ddefc07029f022d",
        "index": 4,
        "format": 1,
        "matches": [
          {
            "p1": "674125190253e44912294526",
            "p2": "674124cc6e153ca1279dd0a5",
            "format": 1,
            "games": [
              {
                "p1": 6,
                "p2": 13
              },
              {
                "p1": 6,
                "p2": 13
              }
            ],
            "won": "674124cc6e153ca1279dd0a5",
            "lost": "674125190253e44912294526",
            "diff": 14
          },
          {
            "p1": "67412529b148bf739d49828b",
            "p2": "674125330a62bc77412439f9",
            "format": 1,
            "games": [
              {
                "p1": 16,
                "p2": 14
              },
              {
                "p1": 11,
                "p2": 13
              },
              {
                "p1": 6,
                "p2": 13
              }
            ],
            "won": "674125330a62bc77412439f9",
            "lost": "67412529b148bf739d49828b",
            "diff": 7
          },
          {
            "p1": "6741252f4aeabdb5905c3d0c",
            "p2": "67412543c987a8093fa50f3b",
            "format": 1,
            "games": [
              {
                "p1": 13,
                "p2": 10
              },
              {
                "p1": 13,
                "p2": 9
              }
            ],
            "won": "6741252f4aeabdb5905c3d0c",
            "lost": "67412543c987a8093fa50f3b",
            "diff": 7
          }
        ]
      }
    ],
    "owner": "674117eee1d0fe2f52522080",
    "startedAt": "2024-11-22T00:00:00Z",
    "createdAt": 1667678539544,
    "createdBy": "674117eee1d0fe2f52522080",
    "completed": false,
    "deleted": false
  }
]